yoyo/__init__.py
yoyo/__main__.py
yoyo/config.py
yoyo/connections.py
yoyo/exceptions.py
yoyo/migrations.py
yoyo/topologicalsort.py
yoyo/utils.py
yoyo/backends/__init__.py
yoyo/backends/base.py
yoyo/backends/contrib/__init__.py
yoyo/backends/contrib/odbc.py
yoyo/backends/contrib/oracle.py
yoyo/backends/contrib/redshift.py
yoyo/backends/contrib/snowflake.py
yoyo/backends/core/__init__.py
yoyo/backends/core/mysql.py
yoyo/backends/core/postgresql.py
yoyo/backends/core/sqlite3.py
yoyo/internalmigrations/__init__.py
yoyo/internalmigrations/v1.py
yoyo/internalmigrations/v2.py
yoyo/scripts/__init__.py
yoyo/scripts/init.py
yoyo/scripts/main.py
yoyo/scripts/migrate.py
yoyo/scripts/newmigration.py
yoyo/tests/migrations/test-pkg-migration.py
yoyo_migrations-8.1.0.dist-info/LICENSE.txt
yoyo_migrations-8.1.0.dist-info/METADATA
yoyo_migrations-8.1.0.dist-info/WHEEL
yoyo_migrations-8.1.0.dist-info/entry_points.txt
yoyo_migrations-8.1.0.dist-info/top_level.txt
yoyo_migrations-8.1.0.dist-info/RECORD
