Metadata-Version: 2.1
Name: yoyo-migrations
Version: 8.1.0
Summary: Database migrations with SQL
Home-page: https://ollycope.com/software/yoyo/latest/
Author: Oliver Cope
Author-email: oliver@redgecko.org
License: Apache
Keywords: migrations migrate database alembic south
Classifier: Development Status :: 5 - Production/Stable
Classifier: Environment :: Console
Classifier: Intended Audience :: Developers
Classifier: License :: OSI Approved :: Apache Software License
Classifier: Operating System :: OS Independent
Classifier: Topic :: Database
Classifier: Topic :: Database :: Front-Ends
Classifier: Topic :: Software Development
Classifier: Topic :: Software Development :: Version Control
Classifier: Programming Language :: Python :: 3
License-File: LICENSE.txt
Requires-Dist: sqlparse
Requires-Dist: tabulate
Requires-Dist: importlib-metadata
Provides-Extra: mysql
Requires-Dist: PyMySQL ; extra == 'mysql'
Provides-Extra: postgres
Requires-Dist: psycopg2 ; extra == 'postgres'
Provides-Extra: pyodbc
Requires-Dist: pyodbc ; extra == 'pyodbc'
